rti_jogo_da_velha/__init__.py
rti_jogo_da_velha/gui.py
rti_jogo_da_velha/jogo_da_velha.py
rti_jogo_da_velha/main.py
rti_jogo_da_velha/minimax.py
rti_jogodavelha-0.0.1.dist-info/LICENSE
rti_jogodavelha-0.0.1.dist-info/METADATA
rti_jogodavelha-0.0.1.dist-info/WHEEL
rti_jogodavelha-0.0.1.dist-info/top_level.txt
rti_jogodavelha-0.0.1.dist-info/RECORD
