Metadata-Version: 2.1
Name: rti-jogodavelha
Version: 0.0.1
Summary: Exemplo de jogo da velha em python
Home-page: https://github.com/robson-tazinaffo/ciencia-dados-python/tree/main/modulo2/Desafio2
Author: Mauro Robson Tazinaffo
Author-email: robsontazinaffo@hotmail.com
License: MIT License
Requires-Python: >=3.8
License-File: LICENSE
